{
	"inputs" : 
	[
		{
			"path" : "CMakeLists.txt"
		},
		{
			"isGenerated" : true,
			"path" : "build/CMakeFiles/3.24.0-rc4/CMakeSystem.cmake"
		},
		{
			"isExternal" : true,
			"path" : "C:/vcpkg/scripts/buildsystems/vcpkg.cmake"
		},
		{
			"isCMake" : true,
			"isExternal" : true,
			"path" : "C:/Program Files/CMake/share/cmake-3.24/Modules/CMakeDependentOption.cmake"
		},
		{
			"isCMake" : true,
			"isExternal" : true,
			"path" : "C:/Program Files/CMake/share/cmake-3.24/Modules/CMakeSystemSpecificInitialize.cmake"
		},
		{
			"isGenerated" : true,
			"path" : "build/CMakeFiles/3.24.0-rc4/CMakeCCompiler.cmake"
		},
		{
			"isGenerated" : true,
			"path" : "build/CMakeFiles/3.24.0-rc4/CMakeCXXCompiler.cmake"
		},
		{
			"isCMake" : true,
			"isExternal" : true,
			"path" : "C:/Program Files/CMake/share/cmake-3.24/Modules/CMakeSystemSpecificInformation.cmake"
		},
		{
			"isCMake" : true,
			"isExternal" : true,
			"path" : "C:/Program Files/CMake/share/cmake-3.24/Modules/CMakeGenericSystem.cmake"
		},
		{
			"isCMake" : true,
			"isExternal" : true,
			"path" : "C:/Program Files/CMake/share/cmake-3.24/Modules/CMakeInitializeConfigs.cmake"
		},
		{
			"isCMake" : true,
			"isExternal" : true,
			"path" : "C:/Program Files/CMake/share/cmake-3.24/Modules/Platform/Windows.cmake"
		},
		{
			"isCMake" : true,
			"isExternal" : true,
			"path" : "C:/Program Files/CMake/share/cmake-3.24/Modules/Platform/WindowsPaths.cmake"
		},
		{
			"isCMake" : true,
			"isExternal" : true,
			"path" : "C:/Program Files/CMake/share/cmake-3.24/Modules/CMakeCInformation.cmake"
		},
		{
			"isCMake" : true,
			"isExternal" : true,
			"path" : "C:/Program Files/CMake/share/cmake-3.24/Modules/CMakeLanguageInformation.cmake"
		},
		{
			"isCMake" : true,
			"isExternal" : true,
			"path" : "C:/Program Files/CMake/share/cmake-3.24/Modules/Compiler/GNU-C.cmake"
		},
		{
			"isCMake" : true,
			"isExternal" : true,
			"path" : "C:/Program Files/CMake/share/cmake-3.24/Modules/Compiler/GNU.cmake"
		},
		{
			"isCMake" : true,
			"isExternal" : true,
			"path" : "C:/Program Files/CMake/share/cmake-3.24/Modules/Compiler/CMakeCommonCompilerMacros.cmake"
		},
		{
			"isCMake" : true,
			"isExternal" : true,
			"path" : "C:/Program Files/CMake/share/cmake-3.24/Modules/Platform/Windows-GNU-C.cmake"
		},
		{
			"isCMake" : true,
			"isExternal" : true,
			"path" : "C:/Program Files/CMake/share/cmake-3.24/Modules/Platform/Windows-GNU.cmake"
		},
		{
			"isGenerated" : true,
			"path" : "build/CMakeFiles/3.24.0-rc4/CMakeRCCompiler.cmake"
		},
		{
			"isCMake" : true,
			"isExternal" : true,
			"path" : "C:/Program Files/CMake/share/cmake-3.24/Modules/CMakeRCInformation.cmake"
		},
		{
			"isCMake" : true,
			"isExternal" : true,
			"path" : "C:/Program Files/CMake/share/cmake-3.24/Modules/Platform/Windows-windres.cmake"
		},
		{
			"isCMake" : true,
			"isExternal" : true,
			"path" : "C:/Program Files/CMake/share/cmake-3.24/Modules/Platform/Windows-GNU-C-ABI.cmake"
		},
		{
			"isCMake" : true,
			"isExternal" : true,
			"path" : "C:/Program Files/CMake/share/cmake-3.24/Modules/CMakeCommonLanguageInclude.cmake"
		},
		{
			"isCMake" : true,
			"isExternal" : true,
			"path" : "C:/Program Files/CMake/share/cmake-3.24/Modules/CMakeCXXInformation.cmake"
		},
		{
			"isCMake" : true,
			"isExternal" : true,
			"path" : "C:/Program Files/CMake/share/cmake-3.24/Modules/CMakeLanguageInformation.cmake"
		},
		{
			"isCMake" : true,
			"isExternal" : true,
			"path" : "C:/Program Files/CMake/share/cmake-3.24/Modules/Compiler/GNU-CXX.cmake"
		},
		{
			"isCMake" : true,
			"isExternal" : true,
			"path" : "C:/Program Files/CMake/share/cmake-3.24/Modules/Compiler/GNU.cmake"
		},
		{
			"isCMake" : true,
			"isExternal" : true,
			"path" : "C:/Program Files/CMake/share/cmake-3.24/Modules/Platform/Windows-GNU-CXX.cmake"
		},
		{
			"isCMake" : true,
			"isExternal" : true,
			"path" : "C:/Program Files/CMake/share/cmake-3.24/Modules/Platform/Windows-GNU.cmake"
		},
		{
			"isCMake" : true,
			"isExternal" : true,
			"path" : "C:/Program Files/CMake/share/cmake-3.24/Modules/Platform/Windows-GNU-CXX-ABI.cmake"
		},
		{
			"isCMake" : true,
			"isExternal" : true,
			"path" : "C:/Program Files/CMake/share/cmake-3.24/Modules/CMakeCommonLanguageInclude.cmake"
		},
		{
			"isExternal" : true,
			"path" : "C:/vcpkg/installed/x86-windows/share/curl/vcpkg-cmake-wrapper.cmake"
		},
		{
			"isExternal" : true,
			"path" : "C:/vcpkg/installed/x86-windows/share/curl/CURLConfigVersion.cmake"
		},
		{
			"isExternal" : true,
			"path" : "C:/vcpkg/installed/x86-windows/share/curl/CURLConfig.cmake"
		},
		{
			"isCMake" : true,
			"isExternal" : true,
			"path" : "C:/Program Files/CMake/share/cmake-3.24/Modules/CMakeFindDependencyMacro.cmake"
		},
		{
			"isExternal" : true,
			"path" : "C:/vcpkg/installed/x86-windows/share/zlib/vcpkg-cmake-wrapper.cmake"
		},
		{
			"isCMake" : true,
			"isExternal" : true,
			"path" : "C:/Program Files/CMake/share/cmake-3.24/Modules/FindZLIB.cmake"
		},
		{
			"isCMake" : true,
			"isExternal" : true,
			"path" : "C:/Program Files/CMake/share/cmake-3.24/Modules/SelectLibraryConfigurations.cmake"
		},
		{
			"isCMake" : true,
			"isExternal" : true,
			"path" : "C:/Program Files/CMake/share/cmake-3.24/Modules/FindPackageHandleStandardArgs.cmake"
		},
		{
			"isCMake" : true,
			"isExternal" : true,
			"path" : "C:/Program Files/CMake/share/cmake-3.24/Modules/FindPackageMessage.cmake"
		},
		{
			"isExternal" : true,
			"path" : "C:/vcpkg/installed/x86-windows/share/curl/CURLTargets.cmake"
		},
		{
			"isExternal" : true,
			"path" : "C:/vcpkg/installed/x86-windows/share/curl/CURLTargets-debug.cmake"
		},
		{
			"isExternal" : true,
			"path" : "C:/vcpkg/installed/x86-windows/share/curl/CURLTargets-release.cmake"
		},
		{
			"isCMake" : true,
			"isExternal" : true,
			"path" : "C:/Program Files/CMake/share/cmake-3.24/Modules/SelectLibraryConfigurations.cmake"
		},
		{
			"isExternal" : true,
			"path" : "C:/vcpkg/installed/x86-windows/share/json-c/json-c-config.cmake"
		},
		{
			"isExternal" : true,
			"path" : "C:/vcpkg/installed/x86-windows/share/json-c/json-c-targets.cmake"
		},
		{
			"isExternal" : true,
			"path" : "C:/vcpkg/installed/x86-windows/share/json-c/json-c-targets-debug.cmake"
		},
		{
			"isExternal" : true,
			"path" : "C:/vcpkg/installed/x86-windows/share/json-c/json-c-targets-release.cmake"
		}
	],
	"kind" : "cmakeFiles",
	"paths" : 
	{
		"build" : "C:/Users/wkell/OneDrive/Documents/projectsc/AVIRclient/build",
		"source" : "C:/Users/wkell/OneDrive/Documents/projectsc/AVIRclient"
	},
	"version" : 
	{
		"major" : 1,
		"minor" : 0
	}
}
